RIAssigner/__init__.py
RIAssigner/__main__.py
RIAssigner/__version__.py
RIAssigner/cli/CreateMethodAction.py
RIAssigner/cli/LoadDataAction.py
RIAssigner/cli/__init__.py
RIAssigner/compute/ComputationMethod.py
RIAssigner/compute/CubicSpline.py
RIAssigner/compute/Kovats.py
RIAssigner/compute/__init__.py
RIAssigner/data/Data.py
RIAssigner/data/MatchMSData.py
RIAssigner/data/PandasData.py
RIAssigner/data/SimpleData.py
RIAssigner/data/ValidateSimpleData.py
RIAssigner/data/__init__.py
RIAssigner/utils.py
riassigner-0.5.0.dist-info/LICENSE
riassigner-0.5.0.dist-info/METADATA
riassigner-0.5.0.dist-info/WHEEL
riassigner-0.5.0.dist-info/RECORD
