Metadata-Version: 2.3
Name: RIAssigner
Version: 0.5.0
Summary: Python library for retention index calculation.
License: MIT
Keywords: gas chromatography,mass spectrometry,retention index
Author: Helge Hecht
Author-email: helge.hecht@recetox.muni.cz
Requires-Python: >=3.10,<3.13
Classifier: Development Status :: 2 - Pre-Alpha
Classifier: Intended Audience :: Developers
Classifier: Intended Audience :: Education
Classifier: Intended Audience :: Science/Research
Classifier: License :: OSI Approved :: MIT License
Classifier: Natural Language :: English
Classifier: Programming Language :: Python :: 3
Classifier: Programming Language :: Python :: 3.10
Classifier: Programming Language :: Python :: 3.11
Classifier: Programming Language :: Python :: 3.12
Requires-Dist: fastparquet (>=2023.10.1,<2024.0.0)
Requires-Dist: matchms (>=0.24.1,<0.25.0)
Requires-Dist: numpy
Requires-Dist: pandas
Requires-Dist: pint (>=0.23,<0.24)
Requires-Dist: scipy
Requires-Dist: urllib3 (==1.26.15)
Project-URL: Repository, https://github.com/RECETOX/RIAssigner
